[
    {
        "version": "1.0(1)",
        "releaseDate": "10 Aug 2018",
        "releaseNotes": "Release 1",
        "url": "https://172.20.219.72/BuildsData/builds/app-release.apk"
    },
    {
        "version": "1.0(2)",
        "releaseDate": "11 Aug 2018",
        "releaseNotes": "Release 2",
        "url": "https://172.20.219.72/BuildsData/builds/app-release.apk"
    },
    {
        "version": "1.0(3)",
        "releaseDate": "12 Aug 2018",
        "releaseNotes": "Release 3",
        "url": "https://172.20.219.72/BuildsData/builds/app-release.apk"
    },
    {
        "version": "1.0(4)",
        "releaseDate": "13 Aug 2018",
        "releaseNotes": "Release 4",
        "url": "https://172.20.219.72/BuildsData/builds/app-release.apk"
    },
    {
        "version": "1.0(5)",
        "releaseDate": "14 Aug 2018",
        "releaseNotes": "Release 5",
        "url": "https://172.20.219.72/BuildsData/builds/app-release.apk"
    },
    {
        "version": "1.0(6)",
        "releaseDate": "15 Aug 2018",
        "releaseNotes": "Release 6",
        "url": "https://172.20.219.72/BuildsData/builds/app-release.apk"
    },
    {
        "version": "1.0(7)",
        "releaseDate": "16 Aug 2018",
        "releaseNotes": "Release 7",
        "url": "https://172.20.219.72/BuildsData/builds/app-release.apk"
    }
]